{"id":"900091294","name":"王富贵杨荣华","followers":1,"total_return":176.75,"daily_return":0.91,"weekly_return":4.75,"monthly_return":-17.19,"yearly_return":112.69,"net_value":2.768,"max_drawdown":32.76,"win_rate":0.0,"days":2042,"concept":"","intro":"","labels":[],"ranks":["年榜"],"total_position":100.0,"quality":true,"positions":[{"stock_name":"芯片ETF","stock_code":"512760","cost_price":0.587,"current_price":1.21,"profit_ratio":106.17,"position_ratio":100.0}],"trades":[{"trade_date":"2021-01-26","direction":"卖出","stock_name":"厦门钨业","stock_code":"600549","trades_count":1,"position_ratio":"9成以上"}],"inferred":[]}