{"id":"900003071","name":"济夜草原","followers":2,"total_return":4095.43,"daily_return":-3.85,"weekly_return":2.76,"monthly_return":-2.67,"yearly_return":9.18,"net_value":41.954,"max_drawdown":84.43,"win_rate":0.0,"days":3236,"concept":"","intro":"","labels":["其他小金属","特钢Ⅱ","垂直应用软件"],"ranks":["总榜"],"total_position":84.0,"quality":false,"positions":[{"stock_name":"东方锆业","stock_code":"002167","cost_price":16.106,"current_price":15.58,"profit_ratio":-3.27,"position_ratio":78.0},{"stock_name":"贵研铂业","stock_code":"600459","cost_price":18.17,"current_price":17.68,"profit_ratio":-2.7,"position_ratio":6.0}],"trades":[{"trade_date":"2026-07-24","direction":"买入","stock_name":"东方锆业","stock_code":"002167","trades_count":3,"position_ratio":"7成"},{"trade_date":"2026-07-24","direction":"卖出","stock_name":"方大特钢","stock_code":"600507","trades_count":1,"position_ratio":"5成"},{"trade_date":"2026-07-24","direction":"买入","stock_name":"远光软件","stock_code":"002063","trades_count":1,"position_ratio":"1成以下"},{"trade_date":"2026-07-24","direction":"买入","stock_name":"安洁科技","stock_code":"002635","trades_count":1,"position_ratio":"1成以下"},{"trade_date":"2026-07-24","direction":"买入","stock_name":"贵研铂业","stock_code":"600459","trades_count":1,"position_ratio":"1成以下"}],"inferred":[{"stock_name":"远光软件","stock_code":"002063","level_estimate":"1成以下","status":"持续买入","confidence":"low","buy_count":1,"sell_count":0},{"stock_name":"安洁科技","stock_code":"002635","level_estimate":"1成以下","status":"持续买入","confidence":"low","buy_count":1,"sell_count":0}]}