{"id":"900054343","name":"20200107金融","followers":2634,"total_return":548.42,"daily_return":-1.27,"weekly_return":-0.39,"monthly_return":7.07,"yearly_return":-11.35,"net_value":6.484,"max_drawdown":34.76,"win_rate":0.0,"days":2392,"concept":"坚持价值投资为主，投机为辅相结合。分散投资，寻找周期性投资机会。","intro":"坚持价值投资为主，投机为辅相结合。分散投资，寻找周期性投资机会。","labels":["城商行Ⅲ","氯碱","环境治理"],"ranks":["总榜"],"total_position":42.0,"quality":false,"positions":[{"stock_name":"北京银行","stock_code":"601169","cost_price":5.34,"current_price":5.06,"profit_ratio":-5.24,"position_ratio":23.0},{"stock_name":"中泰化学","stock_code":"002092","cost_price":5.161,"current_price":4.39,"profit_ratio":-14.95,"position_ratio":19.0}],"trades":[{"trade_date":"2026-07-22","direction":"买入","stock_name":"凯盛科技","stock_code":"600552","trades_count":1,"position_ratio":"1成以下"},{"trade_date":"2026-07-22","direction":"卖出","stock_name":"圣泉转债","stock_code":"111025","trades_count":1,"position_ratio":"1成以下"}],"inferred":[{"stock_name":"凯盛科技","stock_code":"600552","level_estimate":"1成以下","status":"持续买入","confidence":"mid","buy_count":3,"sell_count":0}]}