{"id":"900002741","name":"繁华落寞999","followers":156,"total_return":-83.5,"daily_return":-3.7,"weekly_return":-2.89,"monthly_return":-11.25,"yearly_return":153.5,"net_value":0.165,"max_drawdown":93.91,"win_rate":0.0,"days":3244,"concept":"该理性要理性，该冲动要冲动。","intro":"该理性要理性，该冲动要冲动。","labels":["有色金属"],"ranks":["年榜"],"total_position":90.0,"quality":true,"positions":[{"stock_name":"中国铀业","stock_code":"001280","cost_price":63.765,"current_price":61.18,"profit_ratio":-4.05,"position_ratio":90.0}],"trades":[{"trade_date":"2026-07-24","direction":"买入","stock_name":"中国铀业","stock_code":"001280","trades_count":1,"position_ratio":"9成以上"},{"trade_date":"2026-07-24","direction":"卖出","stock_name":"中国铀业","stock_code":"001280","trades_count":1,"position_ratio":"9成以上"}],"inferred":[]}