{"id":"900086458","name":"实盘组合0086458","followers":745,"total_return":492.02,"daily_return":-2.89,"weekly_return":-5.07,"monthly_return":-14.02,"yearly_return":67.52,"net_value":5.92,"max_drawdown":32.32,"win_rate":0.0,"days":2103,"concept":"","intro":"","labels":["饮料乳品","游戏Ⅲ","电子化学品Ⅲ"],"ranks":["总榜"],"total_position":77.0,"quality":true,"positions":[{"stock_name":"维维股份","stock_code":"600300","cost_price":3.46,"current_price":3.01,"profit_ratio":-13.01,"position_ratio":45.0},{"stock_name":"冰川网络","stock_code":"300533","cost_price":13.736,"current_price":12.94,"profit_ratio":-5.79,"position_ratio":32.0}],"trades":[{"trade_date":"2026-07-23","direction":"买入","stock_name":"冰川网络","stock_code":"300533","trades_count":1,"position_ratio":"1成"}],"inferred":[]}