{"id":"900156963","name":"新疆伊犁大草原","followers":1121,"total_return":356.0,"daily_return":0.0,"weekly_return":0.0,"monthly_return":0.0,"yearly_return":47.59,"net_value":4.56,"max_drawdown":42.54,"win_rate":0.0,"days":1489,"concept":"","intro":"","labels":[],"ranks":["总榜"],"total_position":0,"quality":true,"positions":[],"trades":[{"trade_date":"2026-02-02","direction":"卖出","stock_name":"国机重装","stock_code":"601399","trades_count":1,"position_ratio":"1成以下"},{"trade_date":"2026-02-02","direction":"卖出","stock_name":"北方稀土","stock_code":"600111","trades_count":1,"position_ratio":"9成以上"}],"inferred":[]}