{"id":"900103316","name":"降解塑料0882","followers":7,"total_return":-85.34,"daily_return":30.67,"weekly_return":35.5,"monthly_return":11.44,"yearly_return":50.75,"net_value":0.147,"max_drawdown":95.13,"win_rate":0.0,"days":1965,"concept":"","intro":"","labels":["基础化工","电子","通信"],"ranks":["日榜"],"total_position":67.0,"quality":true,"positions":[{"stock_name":"滨化股份","stock_code":"601678","cost_price":7.555,"current_price":6.84,"profit_ratio":-9.46,"position_ratio":42.0},{"stock_name":"华天科技","stock_code":"002185","cost_price":18.346,"current_price":17.99,"profit_ratio":-1.94,"position_ratio":25.0}],"trades":[{"trade_date":"2026-07-24","direction":"买入","stock_name":"华天科技","stock_code":"002185","trades_count":1,"position_ratio":"2成"},{"trade_date":"2026-07-24","direction":"卖出","stock_name":"强达电路","stock_code":"301628","trades_count":1,"position_ratio":"2成"}],"inferred":[]}