{"id":"900145104","name":"A股女孩绝不认输","followers":55,"total_return":-26.25,"daily_return":-7.72,"weekly_return":-1.73,"monthly_return":23.1,"yearly_return":-10.06,"net_value":0.738,"max_drawdown":55.21,"win_rate":0.0,"days":1600,"concept":"","intro":"","labels":["计算机","航海装备Ⅲ","综合"],"ranks":["月榜"],"total_position":92.0,"quality":false,"positions":[{"stock_name":"汇金科技","stock_code":"300561","cost_price":18.763,"current_price":17.18,"profit_ratio":-8.44,"position_ratio":92.0},{"stock_name":"亚联发展","stock_code":"002316","cost_price":355.004,"current_price":3.69,"profit_ratio":-98.96,"position_ratio":0.0}],"trades":[{"trade_date":"2026-07-24","direction":"买入","stock_name":"汇金科技","stock_code":"300561","trades_count":1,"position_ratio":"1成以下"},{"trade_date":"2026-07-24","direction":"卖出","stock_name":"天海防务","stock_code":"300008","trades_count":1,"position_ratio":"1成以下"}],"inferred":[]}