{"id":"900355742","name":"勤奋的常皓20","followers":0,"total_return":6.74,"daily_return":1.62,"weekly_return":1.79,"monthly_return":3.07,"yearly_return":6.74,"net_value":1.067,"max_drawdown":13.06,"win_rate":0.0,"days":200,"concept":"","intro":"","labels":[],"ranks":["日榜"],"total_position":100.0,"quality":true,"positions":[{"stock_name":"南芯转债","stock_code":"118070","cost_price":100.0,"current_price":164.034,"profit_ratio":64.03,"position_ratio":62.0},{"stock_name":"曙26发债","stock_code":"754019","cost_price":100.0,"current_price":100.0,"profit_ratio":0.0,"position_ratio":38.0}],"trades":[{"trade_date":"2026-06-23","direction":"卖出","stock_name":"A500东财","stock_code":"159380","trades_count":1,"position_ratio":"2成"},{"trade_date":"2026-06-23","direction":"卖出","stock_name":"农业TH","stock_code":"512620","trades_count":1,"position_ratio":"1成"},{"trade_date":"2026-06-23","direction":"卖出","stock_name":"工业软件","stock_code":"159108","trades_count":1,"position_ratio":"5成"}],"inferred":[]}