{"id":"900424546","name":"股友0715A9261W","followers":14,"total_return":39.74,"daily_return":7.23,"weekly_return":29.39,"monthly_return":7.24,"yearly_return":39.74,"net_value":1.397,"max_drawdown":24.5,"win_rate":0.0,"days":55,"concept":"","intro":"","labels":["通信"],"ranks":["周榜","日榜"],"total_position":1.0,"quality":false,"positions":[{"stock_name":"曙26发债","stock_code":"754019","cost_price":100.0,"current_price":100.0,"profit_ratio":0.0,"position_ratio":1.0},{"stock_name":"锐捷网络","stock_code":"301165","cost_price":0.0,"current_price":132.0,"profit_ratio":0.0,"position_ratio":0.0}],"trades":[{"trade_date":"2026-07-24","direction":"卖出","stock_name":"精测转2","stock_code":"123176","trades_count":3,"position_ratio":"9成以上"},{"trade_date":"2026-07-24","direction":"买入","stock_name":"精测转2","stock_code":"123176","trades_count":3,"position_ratio":"9成以上"},{"trade_date":"2026-07-24","direction":"卖出","stock_name":"锐捷网络","stock_code":"301165","trades_count":1,"position_ratio":"9成以上"}],"inferred":[{"stock_name":"新易盛","stock_code":"300502","level_estimate":"4成","status":"持续买入","confidence":"low","buy_count":1,"sell_count":0},{"stock_name":"运机转债","stock_code":"127092","level_estimate":"3成","status":"可能减持","confidence":"low","buy_count":1,"sell_count":1},{"stock_name":"精测转2","stock_code":"123176","level_estimate":"9成以上","status":"可能减持","confidence":"low","buy_count":1,"sell_count":1}]}